gianlp/__init__.py
gianlp/config.py
gianlp/keras_layers/__init__.py
gianlp/keras_layers/masked_embedding.py
gianlp/logging/__init__.py
gianlp/models/__init__.py
gianlp/models/_health_utils.py
gianlp/models/_report_utils.py
gianlp/models/base_model.py
gianlp/models/keras_wrapper.py
gianlp/models/rnn_digest.py
gianlp/models/trainable_model.py
gianlp/models/text_representations/__init__.py
gianlp/models/text_representations/char_embedding_sequence.py
gianlp/models/text_representations/chars_per_word_sequence.py
gianlp/models/text_representations/fasttext_embedding_sequence.py
gianlp/models/text_representations/mapping_embedding.py
gianlp/models/text_representations/per_chunk_sequencer.py
gianlp/models/text_representations/pre_trained_word_embedding_sequence.py
gianlp/models/text_representations/text_representation.py
gianlp/models/text_representations/trainable_word_embedding_sequence.py
gianlp/types/__init__.py
gianlp/utils/__init__.py
GiaNLP-0.0.3.dist-info/LICENSE
GiaNLP-0.0.3.dist-info/METADATA
GiaNLP-0.0.3.dist-info/WHEEL
GiaNLP-0.0.3.dist-info/top_level.txt
GiaNLP-0.0.3.dist-info/RECORD
