Metadata-Version: 2.1
Name: GiaNLP
Version: 0.0.3
Summary: Natural Language Processing for humans
Home-page: https://jian01.github.io/GiaNLP/
Author: Gianmarco Cafferata
Author-email: gcafferata@fi.uba.ar
License: Apache License
Requires-Dist: gensim >=4.0.0
Requires-Dist: pandas
Requires-Dist: tqdm
Requires-Dist: packaging
